loreroll/__init__.py
loreroll/data/npc.json
loreroll/data/npc.yaml
loreroll/npc.py
rollnpc.py
rollthelore-0.3.2.dist-info/METADATA
rollthelore-0.3.2.dist-info/WHEEL
rollthelore-0.3.2.dist-info/entry_points.txt
rollthelore-0.3.2.dist-info/RECORD
