Metadata-Version: 2.1
Name: rollthelore
Version: 0.3.2
Summary: An unseen servant providing an advantage to DMs/GMs while creating their worlds.
Home-page: https://github.com/geckon/rollthelore
Author: Tomáš Heger
Requires-Python: >=3.7,<4.0
Classifier: Programming Language :: Python :: 3
Classifier: Programming Language :: Python :: 3.7
Classifier: Programming Language :: Python :: 3.8
Classifier: Programming Language :: Python :: 3.9
Classifier: Programming Language :: Python :: 3.10
Classifier: Programming Language :: Python :: 3.11
Requires-Dist: click (>=8.1.3,<9.0.0)
Requires-Dist: strictyaml (>=1.7.3,<2.0.0)
